certbot_dns_he/__init__.py
certbot_dns_he/dns_he.py
certbot_dns_he-1.0.0.dist-info/DESCRIPTION.rst
certbot_dns_he-1.0.0.dist-info/METADATA
certbot_dns_he-1.0.0.dist-info/RECORD
certbot_dns_he-1.0.0.dist-info/WHEEL
certbot_dns_he-1.0.0.dist-info/entry_points.txt
certbot_dns_he-1.0.0.dist-info/metadata.json
certbot_dns_he-1.0.0.dist-info/top_level.txt
