Metadata-Version: 2.0
Name: certbot-dns-he
Version: 1.0.0
Summary: Hurricane Electric DNS Authenticator plugin for Certbot
Home-page: https://github.com/TSaaristo/certbot-dns-he
Author: TSaaristo
Author-email: tero.saaristo@gmail.com
License: MIT
Keywords: certbot dns hurricane-electric dns-01 authenticator api
Platform: UNKNOWN
Classifier: Environment :: Plugins
Classifier: Intended Audience :: System Administrators
Classifier: License :: OSI Approved :: Apache Software License
Classifier: Operating System :: POSIX :: Linux
Classifier: Programming Language :: Python
Classifier: Programming Language :: Python :: 2
Classifier: Programming Language :: Python :: 2.7
Classifier: Programming Language :: Python :: 3
Classifier: Programming Language :: Python :: 3.4
Classifier: Programming Language :: Python :: 3.5
Classifier: Programming Language :: Python :: 3.6
Classifier: Programming Language :: Python :: 3.7
Classifier: Topic :: Internet :: WWW/HTTP
Classifier: Topic :: Security
Classifier: Topic :: System :: Installation/Setup
Classifier: Topic :: System :: Networking
Classifier: Topic :: System :: Systems Administration
Classifier: Topic :: Utilities
Requires-Python: >=2.7, !=3.0.*, !=3.1.*, !=3.2.*, !=3.3.*
Requires-Dist: setuptools
Requires-Dist: certbot (>=0.21.1)
Requires-Dist: zope.interface
Requires-Dist: requests
Requires-Dist: lxml
Requires-Dist: six
Requires-Dist: bs4
